khmernormalizer/__init__.py
khmernormalizer/khnormal.py
khmernormalizer/mappings.py
khmernormalizer/normalizer.py
khmernormalizer-0.0.4.dist-info/LICENSE
khmernormalizer-0.0.4.dist-info/METADATA
khmernormalizer-0.0.4.dist-info/WHEEL
khmernormalizer-0.0.4.dist-info/top_level.txt
khmernormalizer-0.0.4.dist-info/RECORD
