Metadata-Version: 2.1
Name: khmernormalizer
Version: 0.0.4
Summary: A missing toolkit for Khmer Natural Language Processing.
Home-page: https://github.com/seanghay/khmernormalizer
Author: Seanghay Yath
Author-email: seanghay.dev@gmail.com
Classifier: Programming Language :: Python :: 3
Classifier: Operating System :: OS Independent
Classifier: Intended Audience :: Developers
Classifier: Natural Language :: English
Requires-Python: >=3.7
License-File: LICENSE
Requires-Dist: regex
Requires-Dist: emoji (==2.6.0)
Requires-Dist: ftfy (==6.1.1)
